colordoll/colordoll.py
colordoll/__init__.py
colordoll/__version__.py
colordoll-0.1.11.dist-info/WHEEL
colordoll-0.1.11.dist-info/METADATA
colordoll-0.1.11.dist-info/RECORD
