Metadata-Version: 2.4
Name: colordoll
Version: 0.1.11
Summary: Colorize text and data structures in the terminal with ANSI escape codes and themed decorators.
Author: kai gouthro
Author-email: kai gouthro <777603+kaigouthro@users.noreply.github.com>
License-Expression: MIT
Requires-Dist: pyyaml>=6.0.2
Requires-Python: >=3.11
